./.gitignore
./LICENSE
./PKG-INFO
./README.md
./calver_auto_release.py
./pyproject.toml
calver_auto_release-1.0.6.dist-info/METADATA
calver_auto_release-1.0.6.dist-info/WHEEL
calver_auto_release-1.0.6.dist-info/entry_points.txt
calver_auto_release-1.0.6.dist-info/licenses/LICENSE
calver_auto_release-1.0.6.dist-info/RECORD
