Metadata-Version: 2.4
Name: calver-auto-release
Version: 1.0.6
Summary: Automatically create GitHub releases using Calendar Versioning (CalVer)
Project-URL: homepage, https://github.com/basnijholt/calver-auto-release
Project-URL: repository, https://github.com/basnijholt/calver-auto-release
Maintainer-email: Bas Nijholt <bas@nijho.lt>
License: MIT
License-File: LICENSE
Classifier: Development Status :: 4 - Beta
Classifier: Intended Audience :: Developers
Classifier: License :: OSI Approved :: MIT License
Classifier: Operating System :: OS Independent
Classifier: Programming Language :: Python
Classifier: Programming Language :: Python :: 3
Classifier: Programming Language :: Python :: 3.10
Classifier: Programming Language :: Python :: 3.11
Classifier: Programming Language :: Python :: 3.12
Classifier: Programming Language :: Python :: 3.13
Classifier: Topic :: Software Development :: Version Control :: Git
Requires-Python: >=3.10
Requires-Dist: gitpython>=3.1.0
Requires-Dist: packaging>=23.0
Requires-Dist: rich>=13.0.0
Provides-Extra: dev
Requires-Dist: black; extra == 'dev'
Requires-Dist: coverage; extra == 'dev'
Requires-Dist: mypy; extra == 'dev'
Requires-Dist: pre-commit; extra == 'dev'
Requires-Dist: pytest; extra == 'dev'
Requires-Dist: pytest-cov; extra == 'dev'
Requires-Dist: pyyaml; extra == 'dev'
Requires-Dist: ruff; extra == 'dev'
Requires-Dist: versioningit; extra == 'dev'
Provides-Extra: test
Requires-Dist: coverage; extra == 'test'
Requires-Dist: pytest; extra == 'test'
Requires-Dist: pytest-cov; extra == 'test'
Requires-Dist: pyyaml; extra == 'test'
Requires-Dist: versioningit; extra == 'test'
